bencoder.cpython-310-s390x-linux-gnu.so
bencoder.pyx-3.0.1.dist-info/top_level.txt
bencoder.pyx-3.0.1.dist-info/METADATA
bencoder.pyx-3.0.1.dist-info/LICENSE
bencoder.pyx-3.0.1.dist-info/RECORD
bencoder.pyx-3.0.1.dist-info/WHEEL
